reese_file_utils.cpython-310-x86_64-linux-gnu.so
reese_file_utils-0.3.21.dist-info/WHEEL
reese_file_utils-0.3.21.dist-info/top_level.txt
reese_file_utils-0.3.21.dist-info/RECORD
reese_file_utils-0.3.21.dist-info/LICENSE
reese_file_utils-0.3.21.dist-info/METADATA
