Metadata-Version: 2.1
Name: reese-file-utils
Version: 0.3.21
Summary: A toolkit for operating files by using Python, set several formats files to markdown format.
Home-page: https://gitee.com/reeseimk/file_utils
Author: reese
Author-email: reeseimk@163.com
Classifier: Programming Language :: Python :: 3
License-File: LICENSE
Requires-Dist: pandas
Requires-Dist: pillow
Requires-Dist: chardet
Requires-Dist: numpy
Requires-Dist: openpyxl
Requires-Dist: opencv-python
